setup.py
test_setj/__init__.py
test_setj/temp_text.py
test_setj.egg-info/PKG-INFO
test_setj.egg-info/SOURCES.txt
test_setj.egg-info/dependency_links.txt
test_setj.egg-info/not-zip-safe
test_setj.egg-info/requires.txt
test_setj.egg-info/top_level.txt