Metadata-Version: 1.0
Name: test-setj
Version: 0.6
Summary: Demo python package for testing how setuptools work
Home-page: https://github.com/apatniv/test_setj
Author: vivek
Author-email: apatniv@gmail.com
License: MIT
Platform: UNKNOWN
